edx_oauth2_provider/__init__.py
edx_oauth2_provider/admin.py
edx_oauth2_provider/backends.py
edx_oauth2_provider/constants.py
edx_oauth2_provider/forms.py
edx_oauth2_provider/models.py
edx_oauth2_provider/urls.py
edx_oauth2_provider/views.py
edx_oauth2_provider/management/__init__.py
edx_oauth2_provider/management/commands/__init__.py
edx_oauth2_provider/management/commands/create_oauth2_client.py
edx_oauth2_provider/migrations/0001_initial.py
edx_oauth2_provider/migrations/__init__.py
edx_oauth2_provider/oidc/__init__.py
edx_oauth2_provider/oidc/collect.py
edx_oauth2_provider/oidc/core.py
edx_oauth2_provider/oidc/handlers.py
edx_oauth2_provider/tests/__init__.py
edx_oauth2_provider/tests/base.py
edx_oauth2_provider/tests/factories.py
edx_oauth2_provider/tests/handlers.py
edx_oauth2_provider/tests/test_create_oauth2_client.py
edx_oauth2_provider/tests/test_credentials.py
edx_oauth2_provider/tests/test_factories.py
edx_oauth2_provider/tests/test_id_token.py
edx_oauth2_provider/tests/test_oidc.py
edx_oauth2_provider/tests/test_trusted.py
edx_oauth2_provider/tests/test_userinfo.py
edx_oauth2_provider/tests/util.py
edx_oauth2_provider-1.3.1.dist-info/AUTHORS
edx_oauth2_provider-1.3.1.dist-info/LICENSE
edx_oauth2_provider-1.3.1.dist-info/METADATA
edx_oauth2_provider-1.3.1.dist-info/WHEEL
edx_oauth2_provider-1.3.1.dist-info/top_level.txt
edx_oauth2_provider-1.3.1.dist-info/RECORD
