Metadata-Version: 2.1
Name: edx-oauth2-provider
Version: 1.3.1
Summary: Provide OAuth2 access to edX installations
Home-page: https://github.com/edx/edx-oauth2-provider
Author: edX
Author-email: UNKNOWN
License: AGPL
Platform: UNKNOWN
Classifier: Development Status :: 3 - Alpha
Classifier: Environment :: Web Environment
Classifier: Intended Audience :: Developers
Classifier: License :: OSI Approved :: GNU Affero General Public License v3
Classifier: Operating System :: OS Independent
Classifier: Programming Language :: Python :: 2
Classifier: Programming Language :: Python :: 2.7
Classifier: Programming Language :: Python :: 3
Classifier: Programming Language :: Python :: 3.6
Classifier: Framework :: Django
Requires-Dist: django (<2.0,>=1.8.7)
Requires-Dist: edx-django-oauth2-provider (<2.0.0,>=1.2.1)
Requires-Dist: PyJWT (<2.0.0,>=1.4.0)
